corv/__init__.py
corv/fit.py
corv/interp.py
corv/models.py
corv/sdss.py
corv/spectral_resampling.py
corv/utils.py
corv/models/warwick_da/500_3D
corv/models/warwick_da/550_3D
corv/models/warwick_da/600_3D
corv/models/warwick_da/650_3D
corv/models/warwick_da/700_3D
corv/models/warwick_da/750_3D
corv/models/warwick_da/800_3D
corv/models/warwick_da/850_3D
corv/models/warwick_da/900_3D
corv-0.2.dist-info/LICENSE
corv-0.2.dist-info/METADATA
corv-0.2.dist-info/WHEEL
corv-0.2.dist-info/top_level.txt
corv-0.2.dist-info/RECORD
