Metadata-Version: 2.1
Name: corv
Version: 0.2
Summary: compact object radial velocities
Author-email: Vedant Chandra <vedant.chandra@cfa.harvard.edu>, Stefan Arseneau <arseneau@bu.edu>
Project-URL: Homepage, https://github.com/vedantchandra/corv
Project-URL: Issues, https://github.com/vedantchandra/corv/issues
Classifier: Programming Language :: Python :: 3
Classifier: License :: OSI Approved :: MIT License
Classifier: Operating System :: OS Independent
Requires-Python: >=3.8
License-File: LICENSE
